amms_planop2xls/__init__.py
amms_planop2xls/amms-planop2xls.png
amms_planop2xls/amms-planop2xls.svg
amms_planop2xls/amms_planop2xls.py
amms_planop2xls/util.py
amms_planop2xls/data/Demo.odt
amms_planop2xls/data/Karta anestezjologiczna.odt
amms_planop2xls/data/Karta dokumentacji postepowania przeciwbolowego.odt
amms_planop2xls/data/Karta znieczulenia A4 zlozona JBozy.odt
amms_planop2xls/data/Okolooperacyjna karta kontrolna.odt
amms_planop2xls-0.7.3.dist-info/DESCRIPTION.rst
amms_planop2xls-0.7.3.dist-info/METADATA
amms_planop2xls-0.7.3.dist-info/RECORD
amms_planop2xls-0.7.3.dist-info/WHEEL
amms_planop2xls-0.7.3.dist-info/metadata.json
amms_planop2xls-0.7.3.dist-info/top_level.txt
