Metadata-Version: 2.0
Name: amms-planop2xls
Version: 0.7.3
Summary: Konwerter plików PDF z planem operacyjnym z systemu Asseco Medical Management Solutions
Home-page: https://github.com/mpasternak/amms-planop2xls
Author: Michał Pasternak
Author-email: michal.dtz@gmail.com
License: MIT license
Keywords: amms_planop2xls
Platform: UNKNOWN
Classifier: Development Status :: 2 - Pre-Alpha
Classifier: Intended Audience :: Developers
Classifier: License :: OSI Approved :: MIT License
Classifier: Natural Language :: English
Classifier: Programming Language :: Python :: 3
Classifier: Programming Language :: Python :: 3.6
Requires-Dist: PyQt5 (==5.8.2)
Requires-Dist: pdf-table-extractor (==0.1.2)
Requires-Dist: secretary (==0.2.14)
Requires-Dist: xlrd (==1.0.0)
Requires-Dist: xlwt (==1.2.0)
